and_tools/__init__.py
and_tools/byte_.py
and_tools/device_infor.py
and_tools/tea.py
and_tools/Jce/__init__.py
and_tools/Jce/bytebuffer.py
and_tools/Jce/exception.py
and_tools/Jce/stream.py
and_tools/Jce/struct.py
and_tools/Jce_b/__init__.py
and_tools/Jce_b/buffer.py
and_tools/Jce_b/head.py
and_tools/Jce_b/jcetypes.py
and_tools/Jce_b/reader.py
and_tools/Jce_b/struct.py
and_tools/Jce_b/typing.py
and_tools/Jce_b/writer.py
and_tools/pack/__init__.py
and_tools/pack/pack.py
and_tools/pack/un_pack.py
and_tools/pb/__init__.py
and_tools/pyproto/__init__.py
android/Tcp.py
android/__init__.py
android/nnx.py
android/http/ClientKey.py
android/http/__init__.py
android/http/accounts.py
android/http/cip.py
android/http/friends.py
android/http/game_credit.py
android/http/headers.py
android/http/level.py
android/http/music.py
android/http/qqsignin.py
android/http/weishi.py
android/im/__init__.py
android/im/oidb/__init__.py
android/im/oidb/OidbSvc_0x88d_1/__init__.py
android/im/oidb/OidbSvc_0xc96/OidbSvc_0xc96_pb2.py
android/im/oidb/OidbSvc_0xc96/__init__.py
android/im/oidb/cmd0x88d/__init__.py
android/im/oidb/cmd0x88d/oidb_0x88d_pb2.py
android/im/oidb/oidb_0xc05/__init__.py
android/im/oidb/oidb_0xc05/oidb_0xc05_pb2.py
android/im/oidb/oidb_sso/__init__.py
android/im/oidb/oidb_sso/oidb_sso_pb2.py
android/im/oidb/qqconnect/__init__.py
android/im/oidb/qqconnect/qqconnect_pb2.py
android/model/__init__.py
android/model/nnx_info.py
android/pack/OidbSvc_0x88d_1.py
android/pack/OidbSvc_0xc05.py
android/pack/OidbSvc_0xc96.py
android/pack/StatSvc_register.py
android/pack/__init__.py
android/pack/trpc_metaverse_mob_proxy_svr_MobProxy_SsoHandle.py
android/pack/SQQzoneSvc/__init__.py
android/pack/SQQzoneSvc/delUgc.py
android/pack/SQQzoneSvc/like.py
android/pack/SQQzoneSvc/publishmood.py
android/pack/SQQzoneSvc/shuoshuo.py
android/pack/SummaryCard/ReqSummaryCard.py
android/pack/SummaryCard/__init__.py
android/struct/__init__.py
android/struct/NS_MOBILE_COMM/UgcRightInfo.py
QCo-0.10.2.dist-info/METADATA
QCo-0.10.2.dist-info/WHEEL
QCo-0.10.2.dist-info/top_level.txt
QCo-0.10.2.dist-info/RECORD
